dimensionalityreductionmethods/__init__.py
dimensionalityreductionmethods/dr_handler.py
dimensionalityreductionmethods/dr_methods.py
dimensionalityreductionmethods-0.1.3.dist-info/LICENSE
dimensionalityreductionmethods-0.1.3.dist-info/METADATA
dimensionalityreductionmethods-0.1.3.dist-info/WHEEL
dimensionalityreductionmethods-0.1.3.dist-info/top_level.txt
dimensionalityreductionmethods-0.1.3.dist-info/RECORD
