Metadata-Version: 2.1
Name: dimensionalityreductionmethods
Version: 0.1.3
Summary: A package for applying, comparing, and visualizing dimensionality reduction methods across various target dimensions.
Home-page: https://github.com/AlexStasik/dimensionalityreductionmethods
Author: Afroditi Natsaridou <asikonats@gmail.com>, Darian Zhang <darianyzhang@gmail.com>
Classifier: Programming Language :: Python :: 3
License-File: LICENSE
Requires-Dist: numpy>=1.19.2
Requires-Dist: matplotlib>=3.3.4
Requires-Dist: scikit-learn>=0.24.2
Requires-Dist: tensorflow>=2.4.0
Requires-Dist: pandas>=1.2.3
Requires-Dist: umap-learn>=0.5.0
Requires-Dist: tabulate>=0.8.9
Requires-Dist: joblib>=1.0.1
Requires-Dist: torch>=1.9.0
Requires-Dist: ipykernel
Requires-Dist: ipywidgets>=7.6.0
